seekdbclient/__init__.py
seekdbclient/client/__init__.py
seekdbclient/client/admin_client.py
seekdbclient/client/base_connection.py
seekdbclient/client/client_base.py
seekdbclient/client/client_oceanbase_server.py
seekdbclient/client/client_seekdb_embedded.py
seekdbclient/client/client_seekdb_server.py
seekdbclient/client/collection.py
seekdbclient/client/database.py
seekdbclient/client/filters.py
seekdbclient/client/meta_info.py
seekdbclient/client/query_result.py
seekdbclient/client/sql_utils.py
seekdbclient/examples/comprehensive_example.py
seekdbclient/examples/simple_example.py
seekdbclient/tests/__init__.py
seekdbclient/tests/test_admin_database_management.py
seekdbclient/tests/test_client_creation.py
seekdbclient/tests/test_collection_dml.py
seekdbclient/tests/test_collection_get.py
seekdbclient/tests/test_collection_hybrid_search.py
seekdbclient/tests/test_collection_query.py
seekdbclient-0.1.0.dev2.dist-info/LICENSE
seekdbclient-0.1.0.dev2.dist-info/METADATA
seekdbclient-0.1.0.dev2.dist-info/WHEEL
seekdbclient-0.1.0.dev2.dist-info/RECORD
