Metadata-Version: 2.1
Name: seekdbclient
Version: 0.1.0.dev2
Summary: A unified Python client for SeekDB that supports embedded, server, and OceanBase connection modes with vector database capabilities.
Home-page: https://github.com/oceanbase/pyseekdb/
License: Apache-2.0
Author: SeekDBClient Team
Requires-Python: >=3.8,<4.0
Classifier: License :: OSI Approved :: Apache Software License
Classifier: Programming Language :: Python :: 3
Classifier: Programming Language :: Python :: 3.8
Classifier: Programming Language :: Python :: 3.9
Classifier: Programming Language :: Python :: 3.10
Classifier: Programming Language :: Python :: 3.11
Classifier: Programming Language :: Python :: 3.12
Classifier: Programming Language :: Python :: 3.13
Requires-Dist: pymysql (>=1.1.1,<2.0.0)
Requires-Dist: seekdb
Project-URL: Bug Tracker, https://github.com/oceanbase/pyseekdb/issues
Project-URL: Repository, https://github.com/oceanbase/pyseekdb/
